{
        "Topology Info" : {
                        "nodes"  : 4,
                        "links"  : 6
                          },
 	"Device_Details": {
      "NCS_R1": {
        "device_type": "cisco_xr",
        "ip": "10.91.126.199",
        "port": "22",
        "username": "averma2",
        "password": "Ank#2018"
      },
      "NCS_R2": {
        "device_type": "cisco_xr",
        "ip": "10.91.126.200",
        "port": "22",
        "username": "averma2",
        "password": "Ank#2018"
      },
	  "LTS_R3": {
        "device_type": "accedian",
        "ip": "10.91.121.83",
        "port": "22",
        "username": "admin",
        "password": "admin"
      },
	  "LTS_R4": {
        "device_type": "accedian",
        "ip": "10.91.121.xx",
        "port": "22",
        "username": "admin",
        "password": "admin"
      }
    },
       "Link_Details": {
         "Link_R1_R2": {
           "R1": "TenGigE0/0/0/11",
           "R2": "TenGigE0/0/0/11"
         },
		 "Link_R3": {
           "R3_1": "PORT-1",
           "R3_5": "PORT-5"
         },
		 "Link_R4": {
           "R4U": "PORT-1",
           "R4N": "PORT-2"
         }
       }
}
